{"copyright":"Copyright 2026 MLB Advanced Media, L.P.  Use of any content on this page acknowledges agreement to the terms posted here http://gdx.mlb.com/components/copyright.txt","people":[{"id":116852,"fullName":"Eric Karros","link":"/api/v1/people/116852","firstName":"Eric","lastName":"Karros","primaryNumber":"23","birthDate":"1967-11-04","currentAge":58,"birthCity":"Hackensack","birthStateProvince":"NJ","birthCountry":"USA","height":"6' 4\"","weight":225,"active":false,"currentTeam":{"id":133,"name":"Oakland Athletics","link":"/api/v1/teams/133"},"primaryPosition":{"code":"3","name":"First Base","type":"Infielder","abbreviation":"1B"},"useName":"Eric","useLastName":"Karros","middleName":"Peter","boxscoreName":"Karros","gender":"M","isPlayer":true,"isVerified":true,"draftYear":1988,"lastPlayedDate":"2004-07-21","mlbDebutDate":"1991-09-01","batSide":{"code":"R","description":"Right"},"pitchHand":{"code":"R","description":"Right"},"nameFirstLast":"Eric Karros","nameSlug":"eric-karros-116852","firstLastName":"Eric Karros","lastFirstName":"Karros, Eric","lastInitName":"Karros, E","initLastName":"E Karros","fullFMLName":"Eric Peter Karros","fullLFMName":"Karros, Eric Peter","strikeZoneTop":3.388,"strikeZoneBottom":1.71}]}