{"copyright":"Copyright 2026 MLB Advanced Media, L.P.  Use of any content on this page acknowledges agreement to the terms posted here http://gdx.mlb.com/components/copyright.txt","people":[{"id":120637,"fullName":"Johnny Podres","link":"/api/v1/people/120637","firstName":"John","lastName":"Podres","primaryNumber":"22","birthDate":"1932-09-30","currentAge":75,"birthCity":"Witherbee","birthStateProvince":"NY","birthCountry":"USA","height":"5' 11\"","weight":190,"active":false,"currentTeam":{"id":135,"name":"San Diego Padres","link":"/api/v1/teams/135"},"primaryPosition":{"code":"1","name":"Pitcher","type":"Pitcher","abbreviation":"P"},"useName":"Johnny","useLastName":"Podres","middleName":"Joseph","boxscoreName":"Podres","gender":"M","isPlayer":true,"isVerified":true,"deathDate":"2008-01-13","deathCity":"Glens Falls","deathStateProvince":"NY","deathCountry":"USA","lastPlayedDate":"1969-06-21","mlbDebutDate":"1953-04-17","batSide":{"code":"L","description":"Left"},"pitchHand":{"code":"L","description":"Left"},"nameFirstLast":"Johnny Podres","nameSlug":"johnny-podres-120637","firstLastName":"Johnny Podres","lastFirstName":"Podres, Johnny","lastInitName":"Podres, J","initLastName":"J Podres","fullFMLName":"John Joseph Podres","fullLFMName":"Podres, John Joseph","strikeZoneTop":3.165,"strikeZoneBottom":1.598}]}