{"copyright":"Copyright 2026 MLB Advanced Media, L.P.  Use of any content on this page acknowledges agreement to the terms posted here http://gdx.mlb.com/components/copyright.txt","people":[{"id":518516,"fullName":"Madison Bumgarner","link":"/api/v1/people/518516","firstName":"Madison","lastName":"Bumgarner","primaryNumber":"40","birthDate":"1989-08-01","currentAge":36,"birthCity":"Hickory","birthStateProvince":"NC","birthCountry":"USA","height":"6' 4\"","weight":240,"active":false,"currentTeam":{"id":109,"name":"Arizona Diamondbacks","link":"/api/v1/teams/109"},"primaryPosition":{"code":"1","name":"Pitcher","type":"Pitcher","abbreviation":"P"},"useName":"Madison","useLastName":"Bumgarner","middleName":"Kyle","boxscoreName":"Bumgarner","nickName":"Mad-Bum","gender":"M","isPlayer":true,"isVerified":true,"draftYear":2007,"pronunciation":"MAD-i-suhn BUHM-gahr-ner","lastPlayedDate":"2023-04-19","mlbDebutDate":"2009-09-08","batSide":{"code":"R","description":"Right"},"pitchHand":{"code":"L","description":"Left"},"nameFirstLast":"Madison Bumgarner","nameSlug":"madison-bumgarner-518516","firstLastName":"Madison Bumgarner","lastFirstName":"Bumgarner, Madison","lastInitName":"Bumgarner, M","initLastName":"M Bumgarner","fullFMLName":"Madison Kyle Bumgarner","fullLFMName":"Bumgarner, Madison Kyle","strikeZoneTop":3.39,"strikeZoneBottom":1.61}]}