{"copyright":"Copyright 2026 MLB Advanced Media, L.P.  Use of any content on this page acknowledges agreement to the terms posted here http://gdx.mlb.com/components/copyright.txt","people":[{"id":277408,"fullName":"Kazuhiro Sasaki","link":"/api/v1/people/277408","firstName":"Kazuhiro","lastName":"Sasaki","birthDate":"1968-02-22","currentAge":58,"birthCity":"Sendai City","birthCountry":"Japan","height":"6' 4\"","weight":220,"active":false,"currentTeam":{"id":136,"name":"Seattle Mariners","link":"/api/v1/teams/136"},"primaryPosition":{"code":"1","name":"Pitcher","type":"Pitcher","abbreviation":"P"},"useName":"Kazuhiro","useLastName":"Sasaki","boxscoreName":"Sasaki","gender":"M","isPlayer":true,"isVerified":true,"lastPlayedDate":"2003-09-28","mlbDebutDate":"2000-04-05","batSide":{"code":"R","description":"Right"},"pitchHand":{"code":"R","description":"Right"},"nameFirstLast":"Kazuhiro Sasaki","nameSlug":"kazuhiro-sasaki-277408","firstLastName":"Kazuhiro Sasaki","lastFirstName":"Sasaki, Kazuhiro","lastInitName":"Sasaki, K","initLastName":"K Sasaki","fullFMLName":"Kazuhiro Sasaki","fullLFMName":"Sasaki, Kazuhiro","strikeZoneTop":3.388,"strikeZoneBottom":1.71}]}