{"copyright":"Copyright 2026 MLB Advanced Media, L.P.  Use of any content on this page acknowledges agreement to the terms posted here http://gdx.mlb.com/components/copyright.txt","stats":[{"type":{"displayName":"yearByYear"},"group":{"displayName":"pitching"},"exemptions":[],"splits":[{"season":"1985","stat":{"age":25,"gamesPlayed":17,"gamesStarted":0,"groundOuts":3,"airOuts":2,"runs":7,"doubles":5,"triples":2,"homeRuns":2,"strikeOuts":17,"baseOnBalls":7,"intentionalWalks":2,"hits":17,"hitByPitch":0,"avg":".215","atBats":79,"obp":".273","slg":".405","ops":".678","caughtStealing":0,"stolenBases":1,"stolenBasePercentage":"1.000","caughtStealingPercentage":".000","groundIntoDoublePlay":2,"numberOfPitches":143,"era":"2.91","inningsPitched":"21.2","wins":3,"losses":0,"saves":5,"saveOpportunities":5,"holds":0,"blownSaves":0,"earnedRuns":7,"whip":"1.11","battersFaced":88,"outs":65,"gamesPitched":17,"completeGames":0,"shutouts":0,"strikes":115,"strikePercentage":".800","hitBatsmen":0,"balks":0,"wildPitches":2,"pickoffs":0,"totalBases":32,"groundOutsToAirouts":"1.50","winPercentage":"1.000","pitchesPerInning":"6.60","gamesFinished":11,"strikeoutWalkRatio":"2.43","strikeoutsPer9Inn":"7.06","walksPer9Inn":"2.91","hitsPer9Inn":"7.06","runsScoredPer9":"2.91","homeRunsPer9":"0.83","inheritedRunners":20,"inheritedRunnersScored":7,"catchersInterference":0,"sacBunts":0,"sacFlies":2},"team":{"id":138,"name":"St. Louis Cardinals","link":"/api/v1/teams/138"},"player":{"id":124581,"fullName":"Todd Worrell","link":"/api/v1/people/124581"},"league":{"id":104,"name":"National League","link":"/api/v1/league/104"},"sport":{"id":1,"link":"/api/v1/sports/1","abbreviation":"MLB"},"gameType":"R"},{"season":"1986","stat":{"age":26,"gamesPlayed":74,"gamesStarted":0,"groundOuts":34,"airOuts":38,"runs":29,"doubles":17,"triples":1,"homeRuns":9,"strikeOuts":73,"baseOnBalls":41,"intentionalWalks":16,"hits":86,"hitByPitch":1,"avg":".229","atBats":375,"obp":".303","slg":".352","ops":".655","caughtStealing":5,"stolenBases":9,"stolenBasePercentage":".643","caughtStealingPercentage":".357","groundIntoDoublePlay":6,"numberOfPitches":699,"era":"2.08","inningsPitched":"103.2","wins":9,"losses":10,"saves":36,"saveOpportunities":36,"holds":0,"blownSaves":0,"earnedRuns":24,"whip":"1.23","battersFaced":430,"outs":311,"gamesPitched":74,"completeGames":0,"shutouts":0,"strikes":534,"strikePercentage":".760","hitBatsmen":1,"balks":0,"wildPitches":1,"pickoffs":0,"totalBases":132,"groundOutsToAirouts":"0.89","winPercentage":".474","pitchesPerInning":"6.74","gamesFinished":60,"strikeoutWalkRatio":"1.78","strikeoutsPer9Inn":"6.34","walksPer9Inn":"3.56","hitsPer9Inn":"7.47","runsScoredPer9":"2.52","homeRunsPer9":"0.78","inheritedRunners":65,"inheritedRunnersScored":15,"catchersInterference":0,"sacBunts":7,"sacFlies":6},"team":{"id":138,"name":"St. Louis Cardinals","link":"/api/v1/teams/138"},"player":{"id":124581,"fullName":"Todd Worrell","link":"/api/v1/people/124581"},"league":{"id":104,"name":"National League","link":"/api/v1/league/104"},"sport":{"id":1,"link":"/api/v1/sports/1","abbreviation":"MLB"},"gameType":"R"},{"season":"1987","stat":{"age":27,"gamesPlayed":75,"gamesStarted":0,"groundOuts":28,"airOuts":45,"runs":29,"doubles":14,"triples":3,"homeRuns":8,"strikeOuts":92,"baseOnBalls":34,"intentionalWalks":11,"hits":86,"hitByPitch":0,"avg":".242","atBats":355,"obp":".307","slg":".366","ops":".673","caughtStealing":1,"stolenBases":11,"stolenBasePercentage":".917","caughtStealingPercentage":".083","groundIntoDoublePlay":7,"numberOfPitches":698,"era":"2.66","inningsPitched":"94.2","wins":8,"losses":6,"saves":33,"saveOpportunities":33,"holds":0,"blownSaves":0,"earnedRuns":28,"whip":"1.27","battersFaced":395,"outs":284,"gamesPitched":75,"completeGames":0,"shutouts":0,"strikes":554,"strikePercentage":".790","hitBatsmen":0,"balks":0,"wildPitches":1,"pickoffs":0,"totalBases":130,"groundOutsToAirouts":"0.62","winPercentage":".571","pitchesPerInning":"7.37","gamesFinished":54,"strikeoutWalkRatio":"2.71","strikeoutsPer9Inn":"8.75","walksPer9Inn":"3.23","hitsPer9Inn":"8.18","runsScoredPer9":"2.76","homeRunsPer9":"0.76","inheritedRunners":66,"inheritedRunnersScored":18,"catchersInterference":0,"sacBunts":4,"sacFlies":2},"team":{"id":138,"name":"St. Louis Cardinals","link":"/api/v1/teams/138"},"player":{"id":124581,"fullName":"Todd Worrell","link":"/api/v1/people/124581"},"league":{"id":104,"name":"National League","link":"/api/v1/league/104"},"sport":{"id":1,"link":"/api/v1/sports/1","abbreviation":"MLB"},"gameType":"R"},{"season":"1988","stat":{"age":28,"gamesPlayed":68,"gamesStarted":0,"groundOuts":58,"airOuts":75,"runs":32,"doubles":17,"triples":1,"homeRuns":7,"strikeOuts":78,"baseOnBalls":34,"intentionalWalks":14,"hits":69,"hitByPitch":1,"avg":".214","atBats":323,"obp":".287","slg":".337","ops":".624","caughtStealing":2,"stolenBases":12,"stolenBasePercentage":".857","caughtStealingPercentage":".143","groundIntoDoublePlay":8,"numberOfPitches":1321,"era":"3.00","inningsPitched":"90.0","wins":5,"losses":9,"saves":32,"saveOpportunities":32,"holds":0,"blownSaves":0,"earnedRuns":30,"whip":"1.14","battersFaced":366,"outs":270,"gamesPitched":68,"completeGames":0,"shutouts":0,"strikes":867,"strikePercentage":".660","hitBatsmen":1,"balks":2,"wildPitches":6,"pickoffs":0,"totalBases":109,"groundOutsToAirouts":"0.77","winPercentage":".357","pitchesPerInning":"14.68","gamesFinished":54,"strikeoutWalkRatio":"2.29","strikeoutsPer9Inn":"7.80","walksPer9Inn":"3.40","hitsPer9Inn":"6.90","runsScoredPer9":"3.20","homeRunsPer9":"0.70","inheritedRunners":49,"inheritedRunnersScored":16,"catchersInterference":0,"sacBunts":3,"sacFlies":5},"team":{"id":138,"name":"St. Louis Cardinals","link":"/api/v1/teams/138"},"player":{"id":124581,"fullName":"Todd Worrell","link":"/api/v1/people/124581"},"league":{"id":104,"name":"National League","link":"/api/v1/league/104"},"sport":{"id":1,"link":"/api/v1/sports/1","abbreviation":"MLB"},"gameType":"R"},{"season":"1989","stat":{"age":29,"gamesPlayed":47,"gamesStarted":0,"groundOuts":54,"airOuts":54,"runs":21,"doubles":13,"triples":1,"homeRuns":4,"strikeOuts":41,"baseOnBalls":26,"intentionalWalks":13,"hits":42,"hitByPitch":0,"avg":".222","atBats":189,"obp":".315","slg":".365","ops":".680","caughtStealing":1,"stolenBases":6,"stolenBasePercentage":".857","caughtStealingPercentage":".143","groundIntoDoublePlay":3,"numberOfPitches":794,"era":"2.96","inningsPitched":"51.2","wins":3,"losses":5,"saves":20,"saveOpportunities":20,"holds":0,"blownSaves":0,"earnedRuns":17,"whip":"1.32","battersFaced":219,"outs":155,"gamesPitched":47,"completeGames":0,"shutouts":0,"strikes":515,"strikePercentage":".650","hitBatsmen":0,"balks":3,"wildPitches":3,"pickoffs":1,"totalBases":69,"groundOutsToAirouts":"1.00","winPercentage":".375","pitchesPerInning":"15.37","gamesFinished":39,"strikeoutWalkRatio":"1.58","strikeoutsPer9Inn":"7.14","walksPer9Inn":"4.53","hitsPer9Inn":"7.32","runsScoredPer9":"3.66","homeRunsPer9":"0.70","inheritedRunners":30,"inheritedRunnersScored":8,"catchersInterference":0,"sacBunts":3,"sacFlies":1},"team":{"id":138,"name":"St. Louis Cardinals","link":"/api/v1/teams/138"},"player":{"id":124581,"fullName":"Todd Worrell","link":"/api/v1/people/124581"},"league":{"id":104,"name":"National League","link":"/api/v1/league/104"},"sport":{"id":1,"link":"/api/v1/sports/1","abbreviation":"MLB"},"gameType":"R"},{"season":"1992","stat":{"age":32,"gamesPlayed":67,"gamesStarted":0,"groundOuts":46,"airOuts":75,"runs":15,"doubles":7,"triples":0,"homeRuns":4,"strikeOuts":64,"baseOnBalls":25,"intentionalWalks":5,"hits":45,"hitByPitch":1,"avg":".198","atBats":227,"obp":".281","slg":".282","ops":".563","caughtStealing":0,"stolenBases":13,"stolenBasePercentage":"1.000","caughtStealingPercentage":".000","groundIntoDoublePlay":3,"numberOfPitches":1049,"era":"2.11","inningsPitched":"64.0","wins":5,"losses":3,"saves":3,"saveOpportunities":3,"holds":0,"blownSaves":0,"earnedRuns":15,"whip":"1.09","battersFaced":256,"outs":192,"gamesPitched":67,"completeGames":0,"shutouts":0,"strikes":656,"strikePercentage":".630","hitBatsmen":1,"balks":1,"wildPitches":1,"pickoffs":0,"totalBases":64,"groundOutsToAirouts":"0.61","winPercentage":".625","pitchesPerInning":"16.39","gamesFinished":14,"strikeoutWalkRatio":"2.56","strikeoutsPer9Inn":"9.00","walksPer9Inn":"3.52","hitsPer9Inn":"6.33","runsScoredPer9":"2.11","homeRunsPer9":"0.56","inheritedRunners":8,"inheritedRunnersScored":2,"catchersInterference":0,"sacBunts":3,"sacFlies":0},"team":{"id":138,"name":"St. Louis Cardinals","link":"/api/v1/teams/138"},"player":{"id":124581,"fullName":"Todd Worrell","link":"/api/v1/people/124581"},"league":{"id":104,"name":"National League","link":"/api/v1/league/104"},"sport":{"id":1,"link":"/api/v1/sports/1","abbreviation":"MLB"},"gameType":"R"},{"season":"1993","stat":{"age":33,"gamesPlayed":35,"gamesStarted":0,"groundOuts":33,"airOuts":46,"runs":28,"doubles":8,"triples":0,"homeRuns":6,"strikeOuts":31,"baseOnBalls":11,"intentionalWalks":1,"hits":46,"hitByPitch":0,"avg":".313","atBats":147,"obp":".348","slg":".490","ops":".838","caughtStealing":1,"stolenBases":9,"stolenBasePercentage":".900","caughtStealingPercentage":".100","groundIntoDoublePlay":5,"numberOfPitches":588,"era":"6.05","inningsPitched":"38.2","wins":1,"losses":1,"saves":5,"saveOpportunities":5,"holds":0,"blownSaves":0,"earnedRuns":26,"whip":"1.47","battersFaced":167,"outs":116,"gamesPitched":35,"completeGames":0,"shutouts":0,"strikes":397,"strikePercentage":".680","hitBatsmen":0,"balks":0,"wildPitches":1,"pickoffs":0,"totalBases":72,"groundOutsToAirouts":"0.72","winPercentage":".500","pitchesPerInning":"15.21","gamesFinished":22,"strikeoutWalkRatio":"2.82","strikeoutsPer9Inn":"7.22","walksPer9Inn":"2.56","hitsPer9Inn":"10.71","runsScoredPer9":"6.52","homeRunsPer9":"1.40","inheritedRunners":13,"inheritedRunnersScored":3,"catchersInterference":0,"sacBunts":3,"sacFlies":6},"team":{"id":119,"name":"Los Angeles Dodgers","link":"/api/v1/teams/119"},"player":{"id":124581,"fullName":"Todd Worrell","link":"/api/v1/people/124581"},"league":{"id":104,"name":"National League","link":"/api/v1/league/104"},"sport":{"id":1,"link":"/api/v1/sports/1","abbreviation":"MLB"},"gameType":"R"},{"season":"1994","stat":{"age":34,"gamesPlayed":38,"gamesStarted":0,"groundOuts":35,"airOuts":44,"runs":21,"doubles":9,"triples":1,"homeRuns":4,"strikeOuts":44,"baseOnBalls":12,"intentionalWalks":1,"hits":37,"hitByPitch":1,"avg":".236","atBats":157,"obp":".291","slg":".382","ops":".673","caughtStealing":0,"stolenBases":6,"stolenBasePercentage":"1.000","caughtStealingPercentage":".000","groundIntoDoublePlay":0,"numberOfPitches":660,"era":"4.29","inningsPitched":"42.0","wins":6,"losses":5,"saves":11,"saveOpportunities":11,"holds":0,"blownSaves":0,"earnedRuns":20,"whip":"1.17","battersFaced":173,"outs":126,"gamesPitched":38,"completeGames":0,"shutouts":0,"strikes":431,"strikePercentage":".650","hitBatsmen":1,"balks":0,"wildPitches":1,"pickoffs":0,"totalBases":60,"groundOutsToAirouts":"0.80","winPercentage":".545","pitchesPerInning":"15.71","gamesFinished":27,"strikeoutWalkRatio":"3.67","strikeoutsPer9Inn":"9.43","walksPer9Inn":"2.57","hitsPer9Inn":"7.93","runsScoredPer9":"4.50","homeRunsPer9":"0.86","inheritedRunners":14,"inheritedRunnersScored":9,"catchersInterference":0,"sacBunts":1,"sacFlies":2},"team":{"id":119,"name":"Los Angeles Dodgers","link":"/api/v1/teams/119"},"player":{"id":124581,"fullName":"Todd Worrell","link":"/api/v1/people/124581"},"league":{"id":104,"name":"National League","link":"/api/v1/league/104"},"sport":{"id":1,"link":"/api/v1/sports/1","abbreviation":"MLB"},"gameType":"R"},{"season":"1995","stat":{"age":35,"gamesPlayed":59,"gamesStarted":0,"groundOuts":50,"airOuts":68,"runs":15,"doubles":6,"triples":0,"homeRuns":4,"strikeOuts":61,"baseOnBalls":19,"intentionalWalks":2,"hits":50,"hitByPitch":1,"avg":".221","atBats":226,"obp":".282","slg":".301","ops":".583","caughtStealing":0,"stolenBases":10,"stolenBasePercentage":"1.000","caughtStealingPercentage":".000","groundIntoDoublePlay":5,"numberOfPitches":909,"era":"2.02","inningsPitched":"62.1","wins":4,"losses":1,"saves":32,"saveOpportunities":32,"holds":0,"blownSaves":0,"earnedRuns":14,"whip":"1.11","battersFaced":249,"outs":187,"gamesPitched":59,"completeGames":0,"shutouts":0,"strikes":604,"strikePercentage":".660","hitBatsmen":1,"balks":0,"wildPitches":2,"pickoffs":0,"totalBases":68,"groundOutsToAirouts":"0.74","winPercentage":".800","pitchesPerInning":"14.58","gamesFinished":53,"strikeoutWalkRatio":"3.21","strikeoutsPer9Inn":"8.81","walksPer9Inn":"2.74","hitsPer9Inn":"7.22","runsScoredPer9":"2.17","homeRunsPer9":"0.58","inheritedRunners":26,"inheritedRunnersScored":10,"catchersInterference":0,"sacBunts":1,"sacFlies":2},"team":{"id":119,"name":"Los Angeles Dodgers","link":"/api/v1/teams/119"},"player":{"id":124581,"fullName":"Todd Worrell","link":"/api/v1/people/124581"},"league":{"id":104,"name":"National League","link":"/api/v1/league/104"},"sport":{"id":1,"link":"/api/v1/sports/1","abbreviation":"MLB"},"gameType":"R"},{"season":"1996","stat":{"age":36,"gamesPlayed":72,"gamesStarted":0,"groundOuts":54,"airOuts":78,"runs":29,"doubles":10,"triples":0,"homeRuns":5,"strikeOuts":66,"baseOnBalls":15,"intentionalWalks":1,"hits":70,"hitByPitch":2,"avg":".265","atBats":264,"obp":".307","slg":".360","ops":".667","caughtStealing":0,"stolenBases":8,"stolenBasePercentage":"1.000","caughtStealingPercentage":".000","groundIntoDoublePlay":1,"numberOfPitches":1004,"era":"3.03","inningsPitched":"65.1","wins":4,"losses":6,"saves":44,"saveOpportunities":44,"holds":0,"blownSaves":0,"earnedRuns":22,"whip":"1.30","battersFaced":285,"outs":196,"gamesPitched":72,"completeGames":0,"shutouts":0,"strikes":672,"strikePercentage":".670","hitBatsmen":2,"balks":1,"wildPitches":4,"pickoffs":0,"totalBases":95,"groundOutsToAirouts":"0.69","winPercentage":".400","pitchesPerInning":"15.37","gamesFinished":67,"strikeoutWalkRatio":"4.40","strikeoutsPer9Inn":"9.09","walksPer9Inn":"2.07","hitsPer9Inn":"9.64","runsScoredPer9":"3.99","homeRunsPer9":"0.69","inheritedRunners":24,"inheritedRunnersScored":10,"catchersInterference":0,"sacBunts":2,"sacFlies":2},"team":{"id":119,"name":"Los Angeles Dodgers","link":"/api/v1/teams/119"},"player":{"id":124581,"fullName":"Todd Worrell","link":"/api/v1/people/124581"},"league":{"id":104,"name":"National League","link":"/api/v1/league/104"},"sport":{"id":1,"link":"/api/v1/sports/1","abbreviation":"MLB"},"gameType":"R"},{"season":"1997","stat":{"age":37,"gamesPlayed":65,"gamesStarted":0,"groundOuts":48,"airOuts":72,"runs":38,"doubles":10,"triples":1,"homeRuns":12,"strikeOuts":61,"baseOnBalls":23,"intentionalWalks":1,"hits":60,"hitByPitch":0,"avg":".250","atBats":240,"obp":".316","slg":".450","ops":".766","caughtStealing":0,"stolenBases":7,"stolenBasePercentage":"1.000","caughtStealingPercentage":".000","groundIntoDoublePlay":2,"numberOfPitches":983,"era":"5.28","inningsPitched":"59.2","wins":2,"losses":6,"saves":35,"saveOpportunities":35,"holds":0,"blownSaves":0,"earnedRuns":35,"whip":"1.39","battersFaced":265,"outs":179,"gamesPitched":65,"completeGames":0,"shutouts":0,"strikes":661,"strikePercentage":".670","hitBatsmen":0,"balks":0,"wildPitches":1,"pickoffs":0,"totalBases":108,"groundOutsToAirouts":"0.67","winPercentage":".250","pitchesPerInning":"16.47","gamesFinished":55,"strikeoutWalkRatio":"2.65","strikeoutsPer9Inn":"9.20","walksPer9Inn":"3.47","hitsPer9Inn":"9.05","runsScoredPer9":"5.73","homeRunsPer9":"1.81","inheritedRunners":11,"inheritedRunnersScored":5,"catchersInterference":0,"sacBunts":2,"sacFlies":0},"team":{"id":119,"name":"Los Angeles Dodgers","link":"/api/v1/teams/119"},"player":{"id":124581,"fullName":"Todd Worrell","link":"/api/v1/people/124581"},"league":{"id":104,"name":"National League","link":"/api/v1/league/104"},"sport":{"id":1,"link":"/api/v1/sports/1","abbreviation":"MLB"},"gameType":"R"}]},{"type":{"displayName":"yearByYear"},"group":{"displayName":"hitting"},"exemptions":[],"splits":[{"season":"1985","stat":{"age":25,"gamesPlayed":17,"groundOuts":0,"airOuts":0,"runs":0,"doubles":0,"triples":0,"homeRuns":0,"strikeOuts":1,"baseOnBalls":0,"intentionalWalks":0,"hits":0,"hitByPitch":0,"avg":".000","atBats":1,"obp":".000","slg":".000","ops":".000","caughtStealing":0,"stolenBases":0,"stolenBasePercentage":".---","caughtStealingPercentage":".---","groundIntoDoublePlay":0,"numberOfPitches":3,"plateAppearances":1,"totalBases":0,"rbi":0,"leftOnBase":2,"sacBunts":0,"sacFlies":0,"babip":".---","groundOutsToAirouts":"-.--","catchersInterference":0,"atBatsPerHomeRun":"-.--"},"team":{"id":138,"name":"St. Louis Cardinals","link":"/api/v1/teams/138"},"player":{"id":124581,"fullName":"Todd Worrell","link":"/api/v1/people/124581"},"league":{"id":104,"name":"National League","link":"/api/v1/league/104"},"sport":{"id":1,"link":"/api/v1/sports/1","abbreviation":"MLB"},"gameType":"R"},{"season":"1986","stat":{"age":26,"gamesPlayed":74,"groundOuts":0,"airOuts":0,"runs":0,"doubles":0,"triples":1,"homeRuns":0,"strikeOuts":5,"baseOnBalls":0,"intentionalWalks":0,"hits":1,"hitByPitch":0,"avg":".143","atBats":7,"obp":".143","slg":".429","ops":".572","caughtStealing":0,"stolenBases":0,"stolenBasePercentage":".---","caughtStealingPercentage":".---","groundIntoDoublePlay":0,"numberOfPitches":17,"plateAppearances":7,"totalBases":3,"rbi":0,"leftOnBase":3,"sacBunts":0,"sacFlies":0,"babip":".500","groundOutsToAirouts":"-.--","catchersInterference":0,"atBatsPerHomeRun":"-.--"},"team":{"id":138,"name":"St. Louis Cardinals","link":"/api/v1/teams/138"},"player":{"id":124581,"fullName":"Todd Worrell","link":"/api/v1/people/124581"},"league":{"id":104,"name":"National League","link":"/api/v1/league/104"},"sport":{"id":1,"link":"/api/v1/sports/1","abbreviation":"MLB"},"gameType":"R"},{"season":"1987","stat":{"age":27,"gamesPlayed":75,"groundOuts":3,"airOuts":1,"runs":0,"doubles":0,"triples":0,"homeRuns":0,"strikeOuts":6,"baseOnBalls":0,"intentionalWalks":0,"hits":1,"hitByPitch":0,"avg":".100","atBats":10,"obp":".100","slg":".100","ops":".200","caughtStealing":0,"stolenBases":0,"stolenBasePercentage":".---","caughtStealingPercentage":".---","groundIntoDoublePlay":1,"numberOfPitches":23,"plateAppearances":11,"totalBases":1,"rbi":0,"leftOnBase":5,"sacBunts":1,"sacFlies":0,"babip":".250","groundOutsToAirouts":"3.00","catchersInterference":0,"atBatsPerHomeRun":"-.--"},"team":{"id":138,"name":"St. Louis Cardinals","link":"/api/v1/teams/138"},"player":{"id":124581,"fullName":"Todd Worrell","link":"/api/v1/people/124581"},"league":{"id":104,"name":"National League","link":"/api/v1/league/104"},"sport":{"id":1,"link":"/api/v1/sports/1","abbreviation":"MLB"},"gameType":"R"},{"season":"1988","stat":{"age":28,"gamesPlayed":68,"groundOuts":0,"airOuts":1,"runs":1,"doubles":0,"triples":0,"homeRuns":0,"strikeOuts":5,"baseOnBalls":1,"intentionalWalks":0,"hits":0,"hitByPitch":0,"avg":".000","atBats":6,"obp":".143","slg":".000","ops":".143","caughtStealing":0,"stolenBases":0,"stolenBasePercentage":".---","caughtStealingPercentage":".---","groundIntoDoublePlay":0,"numberOfPitches":27,"plateAppearances":7,"totalBases":0,"rbi":0,"leftOnBase":8,"sacBunts":0,"sacFlies":0,"babip":".000","groundOutsToAirouts":"0.00","catchersInterference":0,"atBatsPerHomeRun":"-.--"},"team":{"id":138,"name":"St. Louis Cardinals","link":"/api/v1/teams/138"},"player":{"id":124581,"fullName":"Todd Worrell","link":"/api/v1/people/124581"},"league":{"id":104,"name":"National League","link":"/api/v1/league/104"},"sport":{"id":1,"link":"/api/v1/sports/1","abbreviation":"MLB"},"gameType":"R"},{"season":"1989","stat":{"age":29,"gamesPlayed":47,"groundOuts":1,"airOuts":0,"runs":0,"doubles":0,"triples":0,"homeRuns":0,"strikeOuts":1,"baseOnBalls":0,"intentionalWalks":0,"hits":0,"hitByPitch":0,"avg":".000","atBats":1,"obp":".000","slg":".000","ops":".000","caughtStealing":0,"stolenBases":0,"stolenBasePercentage":".---","caughtStealingPercentage":".---","groundIntoDoublePlay":0,"numberOfPitches":4,"plateAppearances":2,"totalBases":0,"rbi":0,"leftOnBase":2,"sacBunts":1,"sacFlies":0,"babip":".---","groundOutsToAirouts":"1.00","catchersInterference":0,"atBatsPerHomeRun":"-.--"},"team":{"id":138,"name":"St. Louis Cardinals","link":"/api/v1/teams/138"},"player":{"id":124581,"fullName":"Todd Worrell","link":"/api/v1/people/124581"},"league":{"id":104,"name":"National League","link":"/api/v1/league/104"},"sport":{"id":1,"link":"/api/v1/sports/1","abbreviation":"MLB"},"gameType":"R"},{"season":"1992","stat":{"age":32,"gamesPlayed":67,"groundOuts":0,"airOuts":0,"runs":0,"doubles":0,"triples":0,"homeRuns":0,"strikeOuts":0,"baseOnBalls":0,"intentionalWalks":0,"hits":0,"hitByPitch":0,"avg":".000","atBats":0,"obp":".000","slg":".000","ops":".000","caughtStealing":0,"stolenBases":0,"stolenBasePercentage":".---","caughtStealingPercentage":".---","groundIntoDoublePlay":0,"numberOfPitches":0,"plateAppearances":0,"totalBases":0,"rbi":0,"leftOnBase":0,"sacBunts":0,"sacFlies":0,"babip":".---","groundOutsToAirouts":"-.--","catchersInterference":0,"atBatsPerHomeRun":"-.--"},"team":{"id":138,"name":"St. Louis Cardinals","link":"/api/v1/teams/138"},"player":{"id":124581,"fullName":"Todd Worrell","link":"/api/v1/people/124581"},"league":{"id":104,"name":"National League","link":"/api/v1/league/104"},"sport":{"id":1,"link":"/api/v1/sports/1","abbreviation":"MLB"},"gameType":"R"},{"season":"1993","stat":{"age":33,"gamesPlayed":35,"groundOuts":0,"airOuts":0,"runs":0,"doubles":0,"triples":0,"homeRuns":0,"strikeOuts":0,"baseOnBalls":0,"intentionalWalks":0,"hits":0,"hitByPitch":0,"avg":".000","atBats":0,"obp":".000","slg":".000","ops":".000","caughtStealing":0,"stolenBases":0,"stolenBasePercentage":".---","caughtStealingPercentage":".---","groundIntoDoublePlay":0,"numberOfPitches":0,"plateAppearances":0,"totalBases":0,"rbi":0,"leftOnBase":0,"sacBunts":0,"sacFlies":0,"babip":".---","groundOutsToAirouts":"-.--","catchersInterference":0,"atBatsPerHomeRun":"-.--"},"team":{"id":119,"name":"Los Angeles Dodgers","link":"/api/v1/teams/119"},"player":{"id":124581,"fullName":"Todd Worrell","link":"/api/v1/people/124581"},"league":{"id":104,"name":"National League","link":"/api/v1/league/104"},"sport":{"id":1,"link":"/api/v1/sports/1","abbreviation":"MLB"},"gameType":"R"},{"season":"1994","stat":{"age":34,"gamesPlayed":38,"groundOuts":0,"airOuts":0,"runs":0,"doubles":0,"triples":0,"homeRuns":0,"strikeOuts":0,"baseOnBalls":0,"intentionalWalks":0,"hits":0,"hitByPitch":0,"avg":".000","atBats":0,"obp":".000","slg":".000","ops":".000","caughtStealing":0,"stolenBases":0,"stolenBasePercentage":".---","caughtStealingPercentage":".---","groundIntoDoublePlay":0,"numberOfPitches":0,"plateAppearances":0,"totalBases":0,"rbi":0,"leftOnBase":0,"sacBunts":0,"sacFlies":0,"babip":".---","groundOutsToAirouts":"-.--","catchersInterference":0,"atBatsPerHomeRun":"-.--"},"team":{"id":119,"name":"Los Angeles Dodgers","link":"/api/v1/teams/119"},"player":{"id":124581,"fullName":"Todd Worrell","link":"/api/v1/people/124581"},"league":{"id":104,"name":"National League","link":"/api/v1/league/104"},"sport":{"id":1,"link":"/api/v1/sports/1","abbreviation":"MLB"},"gameType":"R"},{"season":"1995","stat":{"age":35,"gamesPlayed":59,"groundOuts":0,"airOuts":0,"runs":0,"doubles":0,"triples":0,"homeRuns":0,"strikeOuts":2,"baseOnBalls":0,"intentionalWalks":0,"hits":0,"hitByPitch":0,"avg":".000","atBats":2,"obp":".000","slg":".000","ops":".000","caughtStealing":0,"stolenBases":0,"stolenBasePercentage":".---","caughtStealingPercentage":".---","groundIntoDoublePlay":0,"numberOfPitches":8,"plateAppearances":2,"totalBases":0,"rbi":0,"leftOnBase":5,"sacBunts":0,"sacFlies":0,"babip":".---","groundOutsToAirouts":"-.--","catchersInterference":0,"atBatsPerHomeRun":"-.--"},"team":{"id":119,"name":"Los Angeles Dodgers","link":"/api/v1/teams/119"},"player":{"id":124581,"fullName":"Todd Worrell","link":"/api/v1/people/124581"},"league":{"id":104,"name":"National League","link":"/api/v1/league/104"},"sport":{"id":1,"link":"/api/v1/sports/1","abbreviation":"MLB"},"gameType":"R"},{"season":"1996","stat":{"age":36,"gamesPlayed":72,"groundOuts":0,"airOuts":0,"runs":0,"doubles":0,"triples":0,"homeRuns":0,"strikeOuts":0,"baseOnBalls":0,"intentionalWalks":0,"hits":0,"hitByPitch":0,"avg":".000","atBats":0,"obp":".000","slg":".000","ops":".000","caughtStealing":0,"stolenBases":0,"stolenBasePercentage":".---","caughtStealingPercentage":".---","groundIntoDoublePlay":0,"numberOfPitches":0,"plateAppearances":0,"totalBases":0,"rbi":0,"leftOnBase":0,"sacBunts":0,"sacFlies":0,"babip":".---","groundOutsToAirouts":"-.--","catchersInterference":0,"atBatsPerHomeRun":"-.--"},"team":{"id":119,"name":"Los Angeles Dodgers","link":"/api/v1/teams/119"},"player":{"id":124581,"fullName":"Todd Worrell","link":"/api/v1/people/124581"},"league":{"id":104,"name":"National League","link":"/api/v1/league/104"},"sport":{"id":1,"link":"/api/v1/sports/1","abbreviation":"MLB"},"gameType":"R"},{"season":"1997","stat":{"age":37,"gamesPlayed":65,"groundOuts":0,"airOuts":0,"runs":0,"doubles":0,"triples":0,"homeRuns":0,"strikeOuts":0,"baseOnBalls":0,"intentionalWalks":0,"hits":0,"hitByPitch":0,"avg":".000","atBats":0,"obp":".000","slg":".000","ops":".000","caughtStealing":0,"stolenBases":0,"stolenBasePercentage":".---","caughtStealingPercentage":".---","groundIntoDoublePlay":0,"numberOfPitches":0,"plateAppearances":0,"totalBases":0,"rbi":0,"leftOnBase":0,"sacBunts":0,"sacFlies":0,"babip":".---","groundOutsToAirouts":"-.--","catchersInterference":0,"atBatsPerHomeRun":"-.--"},"team":{"id":119,"name":"Los Angeles Dodgers","link":"/api/v1/teams/119"},"player":{"id":124581,"fullName":"Todd Worrell","link":"/api/v1/people/124581"},"league":{"id":104,"name":"National League","link":"/api/v1/league/104"},"sport":{"id":1,"link":"/api/v1/sports/1","abbreviation":"MLB"},"gameType":"R"}]}]}