{"copyright":"Copyright 2026 MLB Advanced Media, L.P.  Use of any content on this page acknowledges agreement to the terms posted here http://gdx.mlb.com/components/copyright.txt","people":[{"id":136860,"fullName":"Carlos Beltrán","link":"/api/v1/people/136860","firstName":"Carlos","lastName":"Beltrán","primaryNumber":"15","birthDate":"1977-04-24","currentAge":49,"birthCity":"Manati","birthCountry":"Puerto Rico","height":"6' 1\"","weight":215,"active":false,"currentTeam":{"id":117,"name":"Houston Astros","link":"/api/v1/teams/117"},"primaryPosition":{"code":"8","name":"Outfielder","type":"Outfielder","abbreviation":"CF"},"useName":"Carlos","useLastName":"Beltrán","middleName":"Ivan","boxscoreName":"Beltrán","nickName":"Ivan","gender":"M","isPlayer":true,"isVerified":true,"draftYear":1995,"pronunciation":"bel-TRAHN","lastPlayedDate":"2017-10-01","mlbDebutDate":"1998-09-14","batSide":{"code":"S","description":"Switch"},"pitchHand":{"code":"R","description":"Right"},"nameFirstLast":"Carlos Beltrán","nameSlug":"carlos-beltran-136860","firstLastName":"Carlos Beltrán","lastFirstName":"Beltrán, Carlos","lastInitName":"Beltrán, C","initLastName":"C Beltrán","fullFMLName":"Carlos Ivan Beltrán","fullLFMName":"Beltrán, Carlos Ivan","strikeZoneTop":3.255,"strikeZoneBottom":1.643}]}