{"resource":"playerawards","parameters":{"PlayerID":1629027},"resultSets":[{"name":"PlayerAwards","headers":["PERSON_ID","FIRST_NAME","LAST_NAME","TEAM","DESCRIPTION","ALL_NBA_TEAM_NUMBER","SEASON","MONTH","WEEK","CONFERENCE","TYPE","SUBTYPE1","SUBTYPE2","SUBTYPE3"],"rowSet":[[1629027,"Trae","Young","Atlanta Hawks","All-NBA","3","2021-22",null,null,"East","Award","Kia Motors","KIANT",null],[1629027,"Trae","Young","Atlanta Hawks","All-Rookie Team","1","2018-19",null,null,"East","Award","Kia Motors","KIART",null],[1629027,"Trae","Young",null,"NBA All-Star",null,"2019-20",null,null,null,"Award","All-Star",null,null],[1629027,"Trae","Young",null,"NBA All-Star",null,"2021-22",null,null,null,"Award","All-Star",null,null],[1629027,"Trae","Young",null,"NBA All-Star",null,"2023-24",null,null,null,"Award","All-Star",null,null],[1629027,"Trae","Young",null,"NBA All-Star",null,"2024-25",null,null,null,"Award","All-Star",null,null],[1629027,"Trae","Young","Atlanta Hawks","NBA Cup All-Tournament Team","1","2024-25",null,null,"East","Award","Emirates","EMATT",null],[1629027,"Trae","Young","Atlanta Hawks","NBA Player of the Week",null,"2018-19",null,"2019-03-18T00:00:00","East","Award","Kia Motors","KIPWK",null],[1629027,"Trae","Young","Atlanta Hawks","NBA Player of the Week"," ","2019-20",null,"2019-10-21T00:00:00","East","Award","Kia Motors","KIPWK"," "],[1629027,"Trae","Young","Atlanta Hawks","NBA Player of the Week",null,"2020-21",null,"2021-05-10T00:00:00","East","Award","Kia Motors","KIPWK",null],[1629027,"Trae","Young","Atlanta Hawks","NBA Player of the Week",null,"2021-22",null,"2021-11-22T00:00:00","East","Award","Kia Motors","KIPWK",null],[1629027,"Trae","Young","Atlanta Hawks","NBA Player of the Week",null,"2021-22",null,"2022-01-17T00:00:00","East","Award","Kia Motors","KIPWK",null],[1629027,"Trae","Young","Atlanta Hawks","NBA Player of the Week",null,"2021-22",null,"2022-03-28T00:00:00","East","Award","Kia Motors","KIPWK",null],[1629027,"Trae","Young","Atlanta Hawks","NBA Player of the Week",null,"2023-24",null,"2024-01-29T00:00:00","East","Award","Kia Motors","KIPWK",null],[1629027,"Trae","Young","Atlanta Hawks","NBA Player of the Week",null,"2024-25",null,"2025-02-03T00:00:00","East","Award","Kia Motors","KIPWK",null],[1629027,"Trae","Young","Atlanta Hawks","NBA Player of the Week",null,"2024-25",null,"2025-03-03T00:00:00","East","Award","Kia Motors","KIPWK",null],[1629027,"Trae","Young","Atlanta Hawks","NBA Rookie of the Month",null,"2018-19","1/1/2019","1900-01-01T12:00:00","East","Award","Kia Motors","KIRMO",null],[1629027,"Trae","Young","Atlanta Hawks","NBA Rookie of the Month",null,"2018-19","11/1/2018","1900-01-01T12:00:00","East","Award","Kia Motors","KIRMO",null],[1629027,"Trae","Young","Atlanta Hawks","NBA Rookie of the Month",null,"2018-19","2/1/2019","1900-01-01T12:00:00","East","Award","Kia Motors","KIRMO",null],[1629027,"Trae","Young","Atlanta Hawks","NBA Rookie of the Month",null,"2018-19","3/1/2019","1900-01-01T12:00:00","East","Award","Kia Motors","KIRMO",null]]}]}