{"$ref":"http://sports.core.api.espn.com/v2/sports/football/leagues/nfl/seasons/2007/athletes/5569?lang=en&region=us","id":"5569","uid":"s:20~l:28~a:5569","guid":"b0af01b3-d32c-c56b-008c-656c4b45080f","type":"football","alternateIds":{"sdr":"1946486"},"firstName":"Bob","lastName":"Sanders","fullName":"Bob Sanders","displayName":"Bob Sanders","shortName":"B. Sanders","weight":206,"displayWeight":"206 lbs","height":68,"displayHeight":"5' 8\"","age":45,"dateOfBirth":"1981-02-24T08:00Z","debutYear":2004,"links":[{"language":"en-US","rel":["playercard","desktop","athlete"],"href":"https://www.espn.com/nfl/player/_/id/5569/bob-sanders","text":"Player Card","shortText":"Player Card","isExternal":false,"isPremium":false},{"language":"en-US","rel":["stats","desktop","athlete"],"href":"https://www.espn.com/nfl/player/stats/_/id/5569/bob-sanders","text":"Stats","shortText":"Stats","isExternal":false,"isPremium":false},{"language":"en-US","rel":["stats","sportscenter","app","athlete"],"href":"sportscenter://x-callback-url/showClubhouse?uid=s:20~l:28~a:5569&section=stats","text":"Stats","shortText":"Stats","isExternal":false,"isPremium":false},{"language":"en-US","rel":["splits","desktop","athlete"],"href":"https://www.espn.com/nfl/player/splits/_/id/5569/bob-sanders","text":"Splits","shortText":"Splits","isExternal":false,"isPremium":false},{"language":"en-US","rel":["gamelog","desktop","athlete"],"href":"https://www.espn.com/nfl/player/gamelog/_/id/5569/bob-sanders","text":"Game Log","shortText":"Game Log","isExternal":false,"isPremium":false},{"language":"en-US","rel":["gamelog","sportscenter","app","athlete"],"href":"sportscenter://x-callback-url/showClubhouse?uid=s:20~l:28~a:5569&section=gamelog","text":"Game Log","shortText":"Game Log","isExternal":false,"isPremium":false},{"language":"en-US","rel":["news","desktop","athlete"],"href":"https://www.espn.com/nfl/player/news/_/id/5569/bob-sanders","text":"News","shortText":"News","isExternal":false,"isPremium":false},{"language":"en-US","rel":["news","sportscenter","app","athlete"],"href":"sportscenter://x-callback-url/showClubhouse?uid=s:20~l:28~a:5569&section=news","text":"News","shortText":"News","isExternal":false,"isPremium":false},{"language":"en-US","rel":["bio","desktop","athlete"],"href":"https://www.espn.com/nfl/player/bio/_/id/5569/bob-sanders","text":"Bio","shortText":"Bio","isExternal":false,"isPremium":false},{"language":"en-US","rel":["bio","sportscenter","app","athlete"],"href":"sportscenter://x-callback-url/showClubhouse?uid=s:20~l:28~a:5569&section=bio","text":"Bio","shortText":"Bio","isExternal":false,"isPremium":false},{"language":"en-US","rel":["overview","desktop","athlete"],"href":"https://www.espn.com/nfl/player/_/id/5569/bob-sanders","text":"Overview","shortText":"Overview","isExternal":false,"isPremium":false},{"language":"en-US","rel":["overview","sportscenter","app","athlete"],"href":"sportscenter://x-callback-url/showClubhouse?uid=s:20~l:28~a:5569","text":"Overview","shortText":"Overview","isExternal":false,"isPremium":false}],"birthPlace":{"city":"Erie","state":"PA"},"college":{"$ref":"http://sports.core.api.espn.com/v2/colleges/2294?lang=en&region=us"},"slug":"bob-sanders","headshot":{"href":"https://a.espncdn.com/i/headshots/nfl/players/full/5569.png","alt":"Bob Sanders"},"jersey":"31","position":{"$ref":"http://sports.core.api.espn.com/v2/sports/football/leagues/nfl/positions/36?lang=en&region=us","id":"36","name":"Safety","displayName":"Safety","abbreviation":"S","leaf":true,"parent":{"$ref":"http://sports.core.api.espn.com/v2/sports/football/leagues/nfl/positions/35?lang=en&region=us"}},"injuries":[],"linked":true,"team":{"$ref":"http://sports.core.api.espn.com/v2/sports/football/leagues/nfl/seasons/2007/teams/11?lang=en&region=us"},"teams":[{"$ref":"http://sports.core.api.espn.com/v2/sports/football/leagues/nfl/seasons/2007/teams/11?lang=en&region=us"}],"statistics":{"$ref":"http://sports.core.api.espn.com/v2/sports/football/leagues/nfl/seasons/2007/types/2/athletes/5569/statistics?lang=en&region=us"},"notes":{"$ref":"http://sports.core.api.espn.com/v2/sports/football/leagues/nfl/seasons/2007/athletes/5569/notes?lang=en&region=us"},"contracts":{"$ref":"http://sports.core.api.espn.com/v2/sports/football/leagues/nfl/athletes/5569/contracts?lang=en&region=us"},"experience":{"years":8},"collegeAthlete":{"$ref":"http://sports.core.api.espn.com/v2/sports/football/leagues/college-football/athletes/125209?lang=en&region=us"},"active":false,"contract":{"$ref":"http://sports.core.api.espn.com/v2/sports/football/leagues/nfl/athletes/5569/contracts/2007?lang=en&region=us","optionType":0,"salary":514320,"bonus":0,"yearsRemaining":0,"signedThrough":2007,"season":{"$ref":"http://sports.core.api.espn.com/v2/sports/football/leagues/nfl/seasons/2007?lang=en&region=us"},"team":{"$ref":"http://sports.core.api.espn.com/v2/sports/football/leagues/nfl/seasons/2007/teams/11?lang=en&region=us"}},"eventLog":{"$ref":"http://sports.core.api.espn.com/v2/sports/football/leagues/nfl/seasons/2007/athletes/5569/eventlog?lang=en&region=us"},"draft":{"displayText":"Year: 2004 Round: 2 Pick: 44","round":2,"year":2004,"selection":44,"team":{"$ref":"http://sports.core.api.espn.com/v2/sports/football/leagues/nfl/seasons/2004/teams/11?lang=en&region=us"}},"status":{"id":"2","name":"Inactive","type":"inactive","abbreviation":"Inactive"}}